longship/client.py
longship/errors.py
longship/types.py
longship_api_client/__init__.py
longship_api_client/api/__init__.py
longship_api_client/api/cdrs/__init__.py
longship_api_client/api/cdrs/cdr_get.py
longship_api_client/api/cdrs/cdr_patch.py
longship_api_client/api/cdrs/get_all_cdrs.py
longship_api_client/api/cdrs/get_all_cdrs_v2.py
longship_api_client/api/cdrs/get_all_interchange_format_v2.py
longship_api_client/api/cdrs/get_all_interchangeformat.py
longship_api_client/api/cdrs/get_file_full_download_cdrs.py
longship_api_client/api/cdrs/get_file_full_download_cdrs_split_by_msp.py
longship_api_client/api/cdrs/get_file_intercharge_cdrs.py
longship_api_client/api/chargepoint_status/__init__.py
longship_api_client/api/chargepoint_status/chargepoint_status_get.py
longship_api_client/api/chargepoint_status/get_all_chargepointstatus.py
longship_api_client/api/chargepointproducts/__init__.py
longship_api_client/api/chargepointproducts/get_all_chargepointproducts.py
longship_api_client/api/chargepointproducts/get_file_chargepointproducts.py
longship_api_client/api/chargepoints/__init__.py
longship_api_client/api/chargepoints/chargepoint_get.py
longship_api_client/api/chargepoints/chargepoint_put.py
longship_api_client/api/chargepoints/chargepointauthorization_get.py
longship_api_client/api/chargepoints/get_all_charge_points_v2.py
longship_api_client/api/chargepoints/get_all_chargepointauthorizations.py
longship_api_client/api/chargepoints/get_all_chargepointmessages.py
longship_api_client/api/chargepoints/get_all_chargepoints.py
longship_api_client/api/commands/__init__.py
longship_api_client/api/commands/send_cancel_reservation_request.py
longship_api_client/api/commands/send_change_availability_request.py
longship_api_client/api/commands/send_change_configuration_request.py
longship_api_client/api/commands/send_clear_cache_request.py
longship_api_client/api/commands/send_clear_charging_profile_request.py
longship_api_client/api/commands/send_data_transfer_request.py
longship-2025.11.12.dist-info/METADATA
longship-2025.11.12.dist-info/WHEEL
longship-2025.11.12.dist-info/licenses/LICENSE
longship-2025.11.12.dist-info/RECORD
